fastcs_goniowl/__init__.py
fastcs_goniowl/__main__.py
fastcs_goniowl/_version.py
fastcs_goniowl/goniowl_controller.py
fastcs_goniowl-0.1.0b4.dist-info/licenses/LICENSE
fastcs_goniowl-0.1.0b4.dist-info/METADATA
fastcs_goniowl-0.1.0b4.dist-info/WHEEL
fastcs_goniowl-0.1.0b4.dist-info/entry_points.txt
fastcs_goniowl-0.1.0b4.dist-info/top_level.txt
fastcs_goniowl-0.1.0b4.dist-info/RECORD
