Metadata-Version: 2.4
Name: fastcs-goniowl
Version: 0.1.0b4
Summary: Sample pin detection for beamline collision prevention
Author-email: James OHea <James.OHea@diamond.ac.uk>
License:                                  Apache License
Project-URL: GitHub, https://github.com/DiamondLightSource/fastcs-goniowl
Classifier: Development Status :: 3 - Alpha
Classifier: License :: OSI Approved :: Apache Software License
Classifier: Programming Language :: Python :: 3.11
Classifier: Programming Language :: Python :: 3.12
Classifier: Programming Language :: Python :: 3.13
Requires-Python: >=3.11
License-File: LICENSE
Requires-Dist: fastcs>=0.10.1
Requires-Dist: opencv-python-headless>=4.12.0.88
Requires-Dist: stdio-socket>=1.3.1
Requires-Dist: tensorflow>=2.20.0
Dynamic: license-file
